Metadata-Version: 2.1
Name: mael
Version: 0.0.3.32
Summary: A tool to convert markdown file to excel.
Home-page: https://github.com/KenjiOhtsuka/mael
Author: Kenji Otsuka
Author-email: kok.fdcm@gmail.com
License: MIT
License-File: LICENSE
